rsrch/__about__.py
rsrch/__init__.py
rsrch/_src/notion.py
rsrch-0.2.5.dist-info/METADATA
rsrch-0.2.5.dist-info/WHEEL
rsrch-0.2.5.dist-info/licenses/LICENSE
rsrch-0.2.5.dist-info/RECORD
