Metadata-Version: 2.1
Name: rsrch
Version: 0.2.5
Summary: Manage your ever-growing list of research papers
Project-URL: Homepage, https://github.com/ishan0102/rsrch
Project-URL: Bug Tracker, https://github.com/ishan0102/rsrch/issues
Author-email: Ishan Shah <ishan0102@utexas.edu>
License-File: LICENSE
Classifier: License :: OSI Approved :: MIT License
Classifier: Operating System :: OS Independent
Classifier: Programming Language :: Python :: 3
Requires-Python: >=3.7
Requires-Dist: arxiv==1.4.2
Requires-Dist: notion-client==2.0.0
Requires-Dist: requests==2.28.1
Requires-Dist: tqdm==4.64.1
